httplib2/__init__.py
httplib2/auth.py
httplib2/cacerts.txt
httplib2/certs.py
httplib2/error.py
httplib2/iri2uri.py
httplib2/socks.py
httplib2-0.20.0.dist-info/LICENSE
httplib2-0.20.0.dist-info/METADATA
httplib2-0.20.0.dist-info/WHEEL
httplib2-0.20.0.dist-info/top_level.txt
httplib2-0.20.0.dist-info/RECORD
